{
  "alpha": 0.6,
  "beta": 0.3,
  "C": 0.05,
  "sigma_psf": 1.5,
  "weight_power": 0.0,
  "N": 372100,
  "N_eff": 22731,
  "block_pix": 4,
  "AICc": {
    "FDB": 313210.19734042423,
    "rot": 424381.03883860563,
    "shift": 326200.6839750023,
    "shuffle": 422669.3570275209
  },
  "chi2": {
    "FDB": 313206.1968124411,
    "rot": 424379.038662619,
    "shift": 326196.6834470192,
    "shuffle": 422669.3570275209
  },
  "rchi2": {
    "FDB": 0.8417303957893918,
    "rot": 1.140500347118963,
    "shift": 0.8766418616789642,
    "shuffle": 1.1359025988377343
  },
  "delta": {
    "FDB_minus_rot": -111170.8414981814,
    "FDB_minus_shift": -12990.48663457809,
    "FDB_minus_shuffle": -109459.15968709666
  },
  "k": {
    "FDB": 2,
    "rot": 1,
    "shift": 2,
    "shuffle": 0
  },
  "sweep": [
    {
      "beta": 0.3,
      "AICc": 4858023.769853153,
      "AICc_shift": 4904998.189527164,
      "Delta_FDB_minus_shift": -46974.41967401095,
      "N": 562500
    },
    {
      "beta": 0.5,
      "AICc": 5012688.757965938,
      "AICc_shift": 5056346.866710418,
      "Delta_FDB_minus_shift": -43658.108744479716,
      "N": 562500
    },
    {
      "beta": 0.7,
      "AICc": 5168899.090960789,
      "AICc_shift": 5210318.9753521,
      "Delta_FDB_minus_shift": -41419.884391311556,
      "N": 562500
    },
    {
      "beta": 0.9,
      "AICc": 5303841.471525929,
      "AICc_shift": 5343186.23309081,
      "Delta_FDB_minus_shift": -39344.76156488061,
      "N": 562500
    }
  ],
  "audit": {
    "xcorr_shift_applied_pix": {
      "dy": 186.0,
      "dx": 186.0
    },
    "controls": {
      "shift_wrap_pix": {
        "dy": 12,
        "dx": -7
      },
      "rng_seed": 42
    }
  },
  "processing": {
    "psf_grid": [
      {
        "sigma_psf": 1.5,
        "weight_power": 0.0,
        "AICc_FDB": 313210.19734042423,
        "AICc_shift": 326200.6839750023,
        "delta_FDB_minus_shift": -12990.48663457809,
        "N": 372100,
        "N_eff": 22731,
        "sigma_floor": 0.6,
        "sigma_scale": 0.6,
        "rho_sum_pos": 7.684717857467817,
        "block_pix_est": 4,
        "align_offset_dy": 0.0,
        "align_offset_dx": 0.0,
        "mask_quantile": 0.7
      },
      {
        "sigma_psf": 1.5,
        "weight_power": 0.3,
        "AICc_FDB": 280924.6312320999,
        "AICc_shift": 288921.66998240625,
        "delta_FDB_minus_shift": -7997.038750306354,
        "N": 372100,
        "N_eff": 22731,
        "sigma_floor": 0.6,
        "sigma_scale": 0.6,
        "rho_sum_pos": 7.684717857467817,
        "block_pix_est": 4,
        "align_offset_dy": 0.0,
        "align_offset_dx": 0.0,
        "mask_quantile": 0.7
      },
      {
        "sigma_psf": 1.5,
        "weight_power": 0.0,
        "AICc_FDB": 313210.19734042423,
        "AICc_shift": 326200.6839750023,
        "delta_FDB_minus_shift": -12990.48663457809,
        "N": 372100,
        "N_eff": 22731,
        "sigma_floor": 0.6,
        "sigma_scale": 0.6,
        "rho_sum_pos": 7.684717857467817,
        "block_pix_est": 4,
        "align_offset_dy": 0.0,
        "align_offset_dx": 0.0,
        "mask_quantile": 0.8
      },
      {
        "sigma_psf": 1.5,
        "weight_power": 0.3,
        "AICc_FDB": 280924.6312320999,
        "AICc_shift": 288921.66998240625,
        "delta_FDB_minus_shift": -7997.038750306354,
        "N": 372100,
        "N_eff": 22731,
        "sigma_floor": 0.6,
        "sigma_scale": 0.6,
        "rho_sum_pos": 7.684717857467817,
        "block_pix_est": 4,
        "align_offset_dy": 0.0,
        "align_offset_dx": 0.0,
        "mask_quantile": 0.8
      }
    ],
    "highpass_grid": [
      {
        "sigma_highpass": 8.0,
        "peak_offset_pix": 159.20113064925135
      }
    ],
    "beta_candidates": [
      0.3,
      0.5,
      0.7,
      0.9
    ],
    "alignment": {
      "method": "lanczos3",
      "dy_pix": 186.0,
      "dx_pix": 186.0,
      "rng_seed": 42
    },
    "fast_mode": true,
    "downsample": 2,
    "dtype": "float32",
    "band_limits": [
      [
        8.0,
        16.0
      ]
    ],
    "se_transform": "none",
    "mask_quantile": 0.7,
    "mask_standard": "top75",
    "mask_robustness": [
      "coverage",
      "top50",
      "top75",
      "top90"
    ],
    "roi_definition": {
      "core_r50": "r <= r50",
      "outer_r75": "r >= r75"
    },
    "block_pix": 4,
    "N_eff": 22731,
    "trim_frac": 0.09,
    "trim_iter": 2,
    "sigma_floor": 0.6,
    "sigma_scale": 0.6,
    "rho_sum_pos": 7.684717857467817,
    "perm": {
      "target": 1200,
      "min": 600,
      "max": 2000,
      "early_stop": true
    },
    "fair_counts": {
      "N": 7396,
      "N_eff": 489,
      "block_pix": 4
    },
    "fair_alignment": {
      "method": "lanczos3",
      "dy_pix": 28.0,
      "dx_pix": 48.0,
      "rng_seed": 42
    },
    "fair_wrap": {
      "dy": 12,
      "dx": -7
    },
    "fair_k_map": {
      "FDB": 2,
      "rot": 1,
      "shift": 2,
      "shuffle": 0
    },
    "fairness_meta": {
      "path": "config/fair.json",
      "sha256": "56f181ae91220909fff30b8ed920503df575a3e9a66b7170f1ab1fbc22d0a814",
      "sha12": "56f181ae9122"
    },
    "command_line": "scripts/reports/make_bullet_holdout.py --train Abell1689,CL0024 --holdout AbellS1063 --sigma-psf 1.5 --sigma-highpass 8 --band 8-16 --fast --block-pix 6",
    "progress_log": "server/public/reports/cluster/AbellS1063_progress.log"
  },
  "wls": {
    "sigma0": 0.6,
    "c": 0.6,
    "block_pix": 4,
    "trim_frac": 0.09,
    "trim_iter": 2,
    "rho_sum_pos_mean": 7.608186660887701
  },
  "indicators": {
    "peak_offset_pix": 154.14927829866735,
    "peak_offset_pix_masked": 154.14927829866735,
    "mask_quantile": 0.7,
    "hp_peak_offset_pix": 159.20113064925135,
    "hp_sigma_pix": 8.0,
    "xcorr_shift_pix": 148.06371720064325,
    "xcorr_peak_offset_pix": 304.69000639994744,
    "peak_distance_kpc": 5258.299732553837,
    "hp_peak_distance_kpc": 5430.627194330912,
    "xcorr_peak_distance_kpc": 10393.505547657964,
    "shear_phase_cos": 0.5724887592317799,
    "corr_residual_sigmae": -0.2895602326054492,
    "spear_r": -0.4759526669381803,
    "spear_p": 0.0,
    "strata": {
      "p50": {
        "thr": 0.19447068870067596,
        "spear_r": -0.2579201671688071,
        "p": 0.0,
        "n": 281250
      },
      "p75": {
        "thr": 0.6849132180213928,
        "spear_r": -0.3243592317614491,
        "p": 0.0,
        "n": 140645
      },
      "p90": {
        "thr": 1.0736912846565247,
        "spear_r": -0.40107497225897276,
        "p": 0.0,
        "n": 56250
      }
    },
    "roi_stats": {
      "global": {
        "pearson_r": -0.2895602326054492,
        "spear_r": -0.4759526669381803,
        "p": 0.0,
        "N": 562500
      },
      "core_r50": {
        "pearson_r": -0.26560619661623164,
        "spear_r": -0.4363936725342548,
        "p": 0.0,
        "N": 281252
      },
      "outer_r75": {
        "pearson_r": -0.33548330638758683,
        "spear_r": -0.44165632049731135,
        "p": 0.0,
        "N": 140629
      }
    },
    "partial_r_given_r": {
      "global": -0.20594370314808863,
      "core_r50": -0.14002083438078683,
      "outer_r75": -0.27769124186776656,
      "pvals": {
        "global": 0.0,
        "core_r50": 0.0,
        "outer_r75": 0.0
      },
      "N": {
        "global": 562500,
        "core_r50": 281252,
        "outer_r75": 140629
      }
    },
    "shadow_metrics": {
      "S_shadow": {
        "global": -0.05769036962797507,
        "core_r50": NaN,
        "outer_r75": -0.06171791136799914
      },
      "Q2": {
        "global": -0.025768518673310523,
        "outer_r75": -0.025686872382065795
      },
      "v_test": {
        "global": {
          "V": 0.057690369625392326,
          "z": 0.9917972667592881,
          "p": 0.37090946835490923
        },
        "outer_r75": {
          "V": 0.061717911365753816,
          "z": 1.1084482697551539,
          "p": 0.330070744654887
        }
      },
      "rayleigh": {
        "R": 0.10391697186020636,
        "z": 3.218023638097286,
        "p": 0.03990245869274189
      },
      "per_band": {
        "band_8_16": {
          "S": -0.05769036962797507,
          "Q2": -0.025768518673310523,
          "weight_sum": 62.34192575274314,
          "n": 298
        }
      },
      "candidates": [
        {
          "tau": 0.11866922112019816,
          "edge_count": 1508,
          "edge_quantile": 0.7,
          "S": -0.05769036962797507,
          "Q2": -0.025768518673310523,
          "p_perm": 0.632279534109817,
          "p_fdr": 0.7886855241264559
        },
        {
          "tau": 0.1993834935229881,
          "edge_count": 256,
          "edge_quantile": NaN,
          "S": -0.34282727998240214,
          "Q2": -0.41929583800834913,
          "p_perm": 0.7886855241264559,
          "p_fdr": 0.7886855241264559
        }
      ],
      "bootstrap": {
        "n": 0
      }
    },
    "S_shadow": {
      "values": {
        "global": -0.05769036962797507,
        "core_r50": NaN,
        "outer_r75": -0.06171791136799914
      },
      "perm": {
        "n": 600,
        "p_perm_one_sided_pos": 0.632279534109817,
        "samples": {
          "mean": -0.0039687116629273985,
          "std": 0.14825174826176857
        },
        "p_fdr": 0.7886855241264559
      },
      "bootstrap": {
        "n": 0
      }
    },
    "boundary_band": {
      "neg_frac": 0.7720231760671633,
      "N": 17961,
      "p_fisher_out_greater": 0.006997579381519577,
      "tau": 0.11866922112019816,
      "delta_tau": 0.011866922112019817,
      "counts": {
        "out": [
          6529,
          8457
        ],
        "in": [
          7188,
          9504
        ]
      }
    },
    "perm_test": {
      "n": 600,
      "effect_d": -2.274985266859331,
      "p_perm_one_sided_neg": 0.009983361064891847
    },
    "bootstrap": {},
    "aux_tot": {
      "spear_r_tot": -0.6177949611543756,
      "spear_p_tot": 0.0,
      "spear_r_tot_p90": -0.41399940306526345,
      "spear_p_tot_p90": 0.0
    },
    "pass": {
      "peak_distance_kpc": {
        "value": 5258.299732553837,
        "thr": 300.0,
        "pass": false
      },
      "peak_distance_kpc_highpass": {
        "value": 5430.627194330912,
        "thr": 300.0,
        "pass": false,
        "hp_sigma": 8.0
      },
      "shear_phase_cos": {
        "value": 0.5724887592317799,
        "thr": 0.2,
        "pass": true
      },
      "neg_corr_global": {
        "spear_r": -0.4759526669381803,
        "p": 0.0,
        "pass": true
      },
      "neg_corr_top10": {
        "spear_r": -0.40107497225897276,
        "p": NaN,
        "pass": false
      }
    }
  },
  "metadata": {
    "generated_at_utc": "2025-09-30T18:24:10.851530+00:00",
    "command": "/home/vagrant/gravitation/.venv/bin/python scripts/reports/make_bullet_holdout.py --train Abell1689,CL0024 --holdout AbellS1063 --sigma-psf 1.5 --sigma-highpass 8 --band 8-16 --fast --block-pix 6",
    "script_sha12": "7f7d74dd9aba",
    "cluster_param_sha8": "6ac5ee58",
    "fair_json_sha256": "56f181ae91220909fff30b8ed920503df575a3e9a66b7170f1ab1fbc22d0a814",
    "fair_json_sha12": "56f181ae9122",
    "shared_params_sha256": "aa694c7f90eafa406021a6777311d0914835eb3b6579409d4ebe57781409d1af",
    "shared_params_sha12": "aa694c7f90ea",
    "rng": {
      "holdout_seed": 42,
      "shadow_control_seed": 42,
      "permutation_n": 600,
      "shadow_permutation_n": 600
    },
    "fast_mode": true,
    "downsample": 2,
    "dtype": "float32",
    "band_limits": [
      [
        8.0,
        16.0
      ]
    ],
    "perm_config": {
      "target": 1200,
      "min": 600,
      "max": 2000,
      "early_stop": true,
      "success_threshold": 0.02,
      "failure_threshold": 0.2
    },
    "shadow_block_pix": 6,
    "env_overrides": {}
  }
}